skip::blank     [\ \t]+
newline     [\n]+
skip::comment     [\#]
colon     [:]
semicolon     [;]
set::version_pyvm     version_pyvm
set::flags     flags
set::filemame     filemame
set::name     name
set::source_size     source_size
set::arg_count     arg_count
set::stack_size     stack_size
set::filename    filename
set::posonly_arg_count     posonly_arg_count
set::kwonly_arg_count     kwonly_arg_count
dir::set     [\.]set
dir::foo     [\.]foo
dir::text     [\.]text
dir::interned     [\.]interned
dir::consts     [\.]consts
dir::names     [\.]names
dir::varnames     [\.]varnames
dir::freevars     [\.]freevars
dir::cellvars     [\.]cellvars
dir::freevars     [\.]freevars
dir::code_start     [\.]code_start
dir::code_end     [\.]code_end
dir::line     [\.]line
pycst::None     None
pycst::True     True
pycst::False     False
keyword::for     for
keyword::while     while
keyword::not     not
keyword::or     or
keyword::if     if
keyword::else     else
integer::hex     [0][x][0-9a-e]+
integer::dec     [+\-]?[0-9]+
complex::float [+\-]?[0-9]+[\.]?[0-9]*[\+][\-]?[0-9]+[\.]?[0-9]*[%][i]
number::float     [+\-]?[0-9]+[\.][0-9]*
number::uint     [0-9]+
string     ".+"
op::sum::plus     [\+]
op::sum::minus     [\-]
op::prod::mul     [\*]
op::prod::div     [/]
paren::left     [(]
paren::right     [)]
brack::left     [[]
brack::right     ]
insn::0::0x00      STOP_CODE
insn::0::0x01      POP_TOP
insn::0::0x02     ROT_TWO
insn::0::0x03      ROT_THREE
insn::0::0x04      DUB_TOP
insn::0::0x05      ROT_FOUR
insn::0::0x09      NOP
insn::0::0x0a      UNARY_POSITIVE
insn::0::0x0b      UNARY_NEGATIVE
insn::0::0x0c      UNARY_NOT
insn::0::0x0d      UNARY_CONVERT
insn::0::0x0f      UNARY_INVERT
insn::0::0x13      BINARY_POWER
insn::0::0x14      BINARY_MULTIPLY
insn::0::0x15      BINARY_DIVIDE
insn::0::0x16      BINARY_MODULO
insn::0::0x17      BINARY_ADD
insn::0::0x18      BINARY_SUBTRACT
insn::0::0x19      BINARY_SUBSCR
insn::0::0x1a      BINARY_FLOOR_DIVIDE
insn::0::0x1b      BINARY_TRUE_DIVIDE
insn::0::0x1c      INPLACE_FLOOR_DIVIDE
insn::0::0x1d      INPLACE_TRUE_DIVIDE
insn::0::0x1e      SLICE
insn::0::0x1f      SLICE_PLUS_1
insn::0::0x20      SLICE_PLUS_2
insn::0::0x21      SLICE_PLUS_3
insn::0::0x28      STORE_SLICE
insn::0::0x29      STORE_SLICE_PLUS_1
insn::0::0x2a      STORE_SLICE_PLUS_2
insn::0::0x2b      STORE_SLICE_PLUS_3
insn::0::0x32      DELETE_SLICE
insn::0::0x33      DELETE_SLICE_PLUS_1
insn::0::0x34      DELETE_SLICE_PLUS_2
insn::0::0x35      DELETE_SLICE_PLUS_3
insn::0::0x36      STORE_MAP
insn::0::0x37      INPLACE_ADD
insn::0::0x38      INPLACE_SUBTRACT
insn::0::0x39      INPLACE_MULTIPLY
insn::0::0x3a      INPLACE_DIVIDE
insn::0::0x3b      INPLACE_MODULO
insn::0::0x3c      STORE_SUBSCR
insn::0::0x3d      DELETE_SUBSCR
insn::0::0x3e      BINARY_LSHIFT
insn::0::0x3f      BINARY_RSHIFT
insn::0::0x40      BINARY_AND
insn::0::0x41      BINARY_XOR
insn::0::0x42      BINARY_OR
insn::0::0x43      INPLACE_POWER
insn::0::0x44      GET_ITER
insn::0::0x46      PRINT_EXPR
insn::0::0x47      PRINT_ITEM
insn::0::0x48      PRINT_NEWLINE
insn::0::0x49      PRINT_ITEM_TO
insn::0::0x4a      PRINT_NEWLINE_TO
insn::0::0x4b      INPLACE_RSHIFT
insn::0::0x4c      INPLACE_LSHIFT
insn::0::0x4d      INPLACE_AND
insn::0::0x4e     INPLACE_OR
insn::0::0x4f      INPLACE_XOR
insn::0::0x50      BREAK_LOOP
insn::0::0x51      WITH_CLEANUP
insn::0::0x52      LOAD_LOCALS
insn::0::0x53      RETURN_VALUE
insn::0::0x54      IMPORT_STAR
insn::0::0x55      EXEC_STMT
insn::0::0x56      YIELD_VALUE
insn::0::0x57      POP_BLOCK
insn::0::0x58      BUILD_CLASS
insn::0::0x59      END_FINALLY
insn::1::0x5a      STORE_NAME
insn::1::0x5b     DELETE_NAME
insn::1::0x5c      UNPACK_SEQUENCE
insn::1::0x5d      FOR_ITER
insn::1::0x5e      LIST_APPEND
insn::1::0x5f      STORE_ATTR
insn::1::0x60      DELETE_ATTR
insn::1::0x61      STORE_GLOBAL
insn::1::0x62      DELETE_GLOBAL
insn::1::0x63      DUP_TOPX
insn::1::0x65      LOAD_NAME
insn::1::0x64      LOAD_CONST
insn::1::0x67      BUILD_LIST
insn::1::0x66      BUILD_TUPLE
insn::1::0x68      BUILD_SET
insn::1::0x6a      LOAD_ATTR
insn::1::0x69      BUILD_MAP
insn::1::0x6b      COMPARE_OP
insn::1::0x6c      IMPORT_NAME
insn::1::0x6d      IMPORT_FROM
insn::1::0x6e      JUMP_FORWARD
insn::1::0x6f      JUMP_IF_FALSE_OR_POP
insn::1::0x70      JUMP_IF_TRUE_OR_POP
insn::1::0x71      JUMP_ABSOLUTE
insn::1::0x72      POP_JUMP_IF_FALSE
insn::1::0x74      LOAD_GLOBAL
insn::1::0x73      POP_JUMP_IF_TRUE
insn::1::0x77      CONTINUE_LOOP
insn::1::0x78      SETUP_LOOP
insn::1::0x79      SETUP_EXCEPT
insn::1::0x7a      SETUP_FINALLY
insn::1::0x7c      LOAD_FAST
insn::1::0x7d      STORE_FAST
insn::1::0x7e      DELETE_FAST
insn::1::0x83      CALL_FUNCTION
insn::1::0x82      RAISE_VARARGS
insn::1::0x84      MAKE_FUNCTION
insn::1::0x85      BUILD_SLICE
insn::1::0x86      MAKE_CLOSURE
insn::1::0x87      LOAD_CLOSURE
insn::1::0x88      LOAD_DEREF
insn::1::0x89      STORE_DEREF
insn::1::0x8c      CALL_FUNCTION_VAR
insn::1::0x8d      CALL_FUNCTION_KW
insn::1::0x8e      CALL_FUNCTION_VAR_KW
insn::1::0x8f      SETUP_WITH
insn::1::0x91      EXTENDED_ARG
insn::1::0x92      SET_ADD
insn::1::0x93      MAP_ADD
symbol     [a-zA-Z_][a-zA-Z_0-9]*
